VERILOG/4_bit_Multiplier.v
// verilog code for a 4 BIT MULTIPLIER using HA and FA

module HA(A, B, SUM, CARRY);

input A, B;
output SUM, CARRY;

assign SUM=A^B;
assign CARRY=(A&B);

endmodule


module FA(A, B, Cin, SUM, CARRY);

input A, B, Cin;
output SUM, CARRY;

assign SUM=(A^B^Cin);
assign CARRY=((A&B)|(A&Cin)|(B&Cin));

endmodule


module Four_Bit_Multiplier(A0, A1, A2, A3, B0, B1, B2, B3, PRODUCT0, PRODUCT1, PRODUCT2, PRODUCT3, PRODUCT4, PRODUCT5, PRODUCT6, PRODUCT7);


input A0, A1, A2, A3;
input B0, B1, B2, B3;
output PRODUCT0, PRODUCT1, PRODUCT2, PRODUCT3, PRODUCT4, PRODUCT5, PRODUCT6, PRODUCT7;

wire HA_a1, HA_b1, HA_a2, HA_b2, HA_a3, HA_b3, HA_a4, HA_b4;
wire FA_a1, FA_b1, FA_c1, FA_a2, FA_b2, FA_c2, FA_a3, FA_b3, FA_c3, FA_a4, FA_b4, FA_c4, FA_a5, FA_b5, FA_c5, FA_a6, FA_b6, FA_c6, FA_a7, FA_b7, FA_c7, FA_a8, FA_b8, FA_c8;

and(PRODUCT0, A0, B0);
and(HA_a1, A0, B1);
and(HA_b1, A1, B0);
and(FA_a1, A0, B2);
and(HA_a2, A2, B0);
and(HA_b2, A1, B1);
and(FA_a3, A1, B2);
and(FA_b2, A0, B3);
and(HA_a4, A3, B0);
and(HA_b4, A2, B1);
and(FA_a7, A2, B2);
and(FA_b7, A3, B1);
and(FA_b4, A1, B3);
and(FA_a8, A2, B3);
and(FA_b8, A3, B2);
and(FA_b6, A3, B3);

HA HA1(HA_a1, HA_b1, PRODUCT1, FA_c1);
HA HA2(HA_a2, HA_b2, FA_b1, FA_c3);
HA HA3(HA_a3, HA_b3, PRODUCT4, FA_c5);
HA HA4(HA_a4, HA_b4, FA_b3, FA_c7);

FA FA1(FA_a1, FA_b1, FA_c1, PRODUCT2, FA_c2);
FA FA2(FA_a2, FA_b2, FA_c2, PRODUCT3, HA_a3);
FA FA3(FA_a3, FA_b3, FA_c3, FA_a2, FA_c4);
FA FA4(FA_a4, FA_b4, FA_c4, HA_b3, FA_a5);
FA FA5(FA_a5, FA_b5, FA_c5, PRODUCT5, FA_c6);
FA FA6(FA_a6, FA_b6, FA_c6, PRODUCT6, PRODUCT7);
FA FA7(FA_a7, FA_b7, FA_c7, FA_a4, FA_c8);
FA FA8(FA_a8, FA_b8, FA_c8, FA_b5, FA_a6);


endmodule

VERILOG/test_bench.v
//Test Bench for checking the functionality of 4_bit_Multiplier.v

`timescale 1ns/10ps

module test_bench();

reg A0;
reg A1;
reg A2;
reg A3;
reg B0;
reg B1;
reg B2;
reg B3;
wire PRODUCT0;
wire PRODUCT1;
wire PRODUCT2;
wire PRODUCT3;
wire PRODUCT4;
wire PRODUCT5;
wire PRODUCT6;
wire PRODUCT7;

Four_Bit_Multiplier UUT (A0, A1, A2, A3, B0, B1, B2, B3, PRODUCT0, PRODUCT1, PRODUCT2, PRODUCT3, PRODUCT4, PRODUCT5, PRODUCT6, PRODUCT7);

integer i;
initial 
    begin

        $dumpfile("test_bench.vcd");
        $dumpvars(0, test_bench);

        A0=0;
        A1=0;
        A2=0;
        A3=0;

        B0=0;
        B1=0;
        B2=0;
        B3=0;    

    end

initial
    begin

        for(i = 1; i < 256; i = i+1) 
        begin

            #1
            {B3, B2, B1, B0, A3, A2, A1, A0} = i;

        end


    end

always @(*)
$display("Time = %0t \n A0 = %b \t A1 = %b \t A2 = %b \t A3 = %b \n B0 = %b \t B1 = %b \t B2 = %b \t B3 = %b", $time, A0,A1,A2,A3,B0,B1,B2,B3);


endmodule

VERILOG/test_bench.vcd
$date
	Tue Nov 29 23:37:55 2022
$end
$version
	Icarus Verilog
$end
$timescale
	10ps
$end
$scope module test_bench $end
$var wire 1 ! PRODUCT7 $end
$var wire 1 " PRODUCT6 $end
$var wire 1 # PRODUCT5 $end
$var wire 1 $ PRODUCT4 $end
$var wire 1 % PRODUCT3 $end
$var wire 1 & PRODUCT2 $end
$var wire 1 ' PRODUCT1 $end
$var wire 1 ( PRODUCT0 $end
$var reg 1 ) A0 $end
$var reg 1 * A1 $end
$var reg 1 + A2 $end
$var reg 1 , A3 $end
$var reg 1 - B0 $end
$var reg 1 . B1 $end
$var reg 1 / B2 $end
$var reg 1 0 B3 $end
$var integer 32 1 i [31:0] $end
$scope module UUT $end
$var wire 1 ) A0 $end
$var wire 1 * A1 $end
$var wire 1 + A2 $end
$var wire 1 , A3 $end
$var wire 1 - B0 $end
$var wire 1 . B1 $end
$var wire 1 / B2 $end
$var wire 1 0 B3 $end
$var wire 1 2 FA_a1 $end
$var wire 1 3 FA_a3 $end
$var wire 1 4 FA_a7 $end
$var wire 1 5 FA_a8 $end
$var wire 1 6 FA_b2 $end
$var wire 1 7 FA_b4 $end
$var wire 1 8 FA_b6 $end
$var wire 1 9 FA_b7 $end
$var wire 1 : FA_b8 $end
$var wire 1 ; HA_a1 $end
$var wire 1 < HA_a2 $end
$var wire 1 = HA_a4 $end
$var wire 1 > HA_b1 $end
$var wire 1 ? HA_b2 $end
$var wire 1 @ HA_b4 $end
$var wire 1 ( PRODUCT0 $end
$var wire 1 ! PRODUCT7 $end
$var wire 1 " PRODUCT6 $end
$var wire 1 # PRODUCT5 $end
$var wire 1 $ PRODUCT4 $end
$var wire 1 % PRODUCT3 $end
$var wire 1 & PRODUCT2 $end
$var wire 1 ' PRODUCT1 $end
$var wire 1 A HA_b3 $end
$var wire 1 B HA_a3 $end
$var wire 1 C FA_c8 $end
$var wire 1 D FA_c7 $end
$var wire 1 E FA_c6 $end
$var wire 1 F FA_c5 $end
$var wire 1 G FA_c4 $end
$var wire 1 H FA_c3 $end
$var wire 1 I FA_c2 $end
$var wire 1 J FA_c1 $end
$var wire 1 K FA_b5 $end
$var wire 1 L FA_b3 $end
$var wire 1 M FA_b1 $end
$var wire 1 N FA_a6 $end
$var wire 1 O FA_a5 $end
$var wire 1 P FA_a4 $end
$var wire 1 Q FA_a2 $end
$scope module FA1 $end
$var wire 1 2 A $end
$var wire 1 I CARRY $end
$var wire 1 & SUM $end
$var wire 1 J Cin $end
$var wire 1 M B $end
$upscope $end
$scope module FA2 $end
$var wire 1 6 B $end
$var wire 1 B CARRY $end
$var wire 1 I Cin $end
$var wire 1 % SUM $end
$var wire 1 Q A $end
$upscope $end
$scope module FA3 $end
$var wire 1 3 A $end
$var wire 1 G CARRY $end
$var wire 1 Q SUM $end
$var wire 1 H Cin $end
$var wire 1 L B $end
$upscope $end
$scope module FA4 $end
$var wire 1 7 B $end
$var wire 1 O CARRY $end
$var wire 1 G Cin $end
$var wire 1 A SUM $end
$var wire 1 P A $end
$upscope $end
$scope module FA5 $end
$var wire 1 O A $end
$var wire 1 E CARRY $end
$var wire 1 # SUM $end
$var wire 1 F Cin $end
$var wire 1 K B $end
$upscope $end
$scope module FA6 $end
$var wire 1 8 B $end
$var wire 1 ! CARRY $end
$var wire 1 E Cin $end
$var wire 1 " SUM $end
$var wire 1 N A $end
$upscope $end
$scope module FA7 $end
$var wire 1 4 A $end
$var wire 1 9 B $end
$var wire 1 C CARRY $end
$var wire 1 P SUM $end
$var wire 1 D Cin $end
$upscope $end
$scope module FA8 $end
$var wire 1 5 A $end
$var wire 1 : B $end
$var wire 1 N CARRY $end
$var wire 1 C Cin $end
$var wire 1 K SUM $end
$upscope $end
$scope module HA1 $end
$var wire 1 ; A $end
$var wire 1 > B $end
$var wire 1 J CARRY $end
$var wire 1 ' SUM $end
$upscope $end
$scope module HA2 $end
$var wire 1 < A $end
$var wire 1 ? B $end
$var wire 1 H CARRY $end
$var wire 1 M SUM $end
$upscope $end
$scope module HA3 $end
$var wire 1 B A $end
$var wire 1 A B $end
$var wire 1 F CARRY $end
$var wire 1 $ SUM $end
$upscope $end
$scope module HA4 $end
$var wire 1 = A $end
$var wire 1 @ B $end
$var wire 1 D CARRY $end
$var wire 1 L SUM $end
$upscope $end
$upscope $end
$upscope $end
$enddefinitions $end
#0
$dumpvars
0Q
0P
0O
0N
0M
0L
0K
0J
0I
0H
0G
0F
0E
0D
0C
0B
0A
0@
0?
0>
0=
0<
0;
0:
09
08
07
06
05
04
03
02
b1 1
00
0/
0.
0-
0,
0+
0*
0)
0(
0'
0&
0%
0$
0#
0"
0!
$end
#100
b10 1
1)
#200
b11 1
1*
0)
#300
b100 1
1)
#400
b101 1
1+
0*
0)
#500
b110 1
1)
#600
b111 1
1*
0)
#700
b1000 1
1)
#800
b1001 1
1,
0+
0*
0)
#900
b1010 1
1)
#1000
b1011 1
1*
0)
#1100
b1100 1
1)
#1200
b1101 1
1+
0*
0)
#1300
b1110 1
1)
#1400
b1111 1
1*
0)
#1500
b10000 1
1)
#1600
b10001 1
1-
0,
0+
0*
0)
#1700
1(
b10010 1
1)
#1800
1'
1>
0(
b10011 1
1*
0)
#1900
1(
b10100 1
1)
#2000
1&
1M
0'
1<
0>
0(
b10101 1
1+
0*
0)
#2100
1(
b10110 1
1)
#2200
1'
1>
0(
b10111 1
1*
0)
#2300
1(
b11000 1
1)
#2400
1%
1Q
0&
1L
0M
0'
1=
0<
0>
0(
b11001 1
1,
0+
0*
0)
#2500
1(
b11010 1
1)
#2600
1'
1>
0(
b11011 1
1*
0)
#2700
1(
b11100 1
1)
#2800
1&
1M
0'
1<
0>
0(
b11101 1
1+
0*
0)
#2900
1(
b11110 1
1)
#3000
1'
1>
0(
b11111 1
1*
0)
#3100
1(
b100000 1
1)
#3200
0%
0Q
0&
0L
0M
0'
0=
0<
0>
0(
b100001 1
1.
0-
0,
0+
0*
0)
#3300
1'
1;
b100010 1
1)
#3400
1&
1M
0'
1?
0;
b100011 1
1*
0)
#3500
1'
1;
b100100 1
1)
#3600
1%
1Q
0&
1L
0M
0'
1@
0?
0;
b100101 1
1+
0*
0)
#3700
1'
1;
b100110 1
1)
#3800
1&
1M
0'
1?
0;
b100111 1
1*
0)
#3900
1'
1;
b101000 1
1)
#4000
1$
0%
1A
0Q
0&
1P
0L
0M
0'
19
0@
0?
0;
b101001 1
1,
0+
0*
0)
#4100
1'
1;
b101010 1
1)
#4200
1&
1M
0'
1?
0;
b101011 1
1*
0)
#4300
1'
1;
b101100 1
1)
#4400
1%
1Q
0&
1L
0M
0'
1@
0?
0;
b101101 1
1+
0*
0)
#4500
1'
1;
b101110 1
1)
#4600
1&
1M
0'
1?
0;
b101111 1
1*
0)
#4700
1'
1;
b110000 1
1)
#4800
0$
0%
0A
0Q
0&
0P
0L
0M
0'
09
0@
0?
0;
b110001 1
1-
0,
0+
0*
0)
#4900
1'
1(
1;
b110010 1
1)
#5000
1&
1M
1>
1?
0(
0;
b110011 1
1*
0)
#5100
1%
1I
0&
0'
1J
1(
1;
b110100 1
1)
#5200
1%
1Q
0I
1&
1L
0J
1<
1@
0>
0?
0(
0;
b110101 1
1+
0*
0)
#5300
1'
1(
1;
b110110 1
1)
#5400
1$
1A
0%
0&
1G
0Q
0M
1H
1>
1?
0(
0;
b110111 1
1*
0)
#5500
1&
0'
1J
1(
1;
b111000 1
1)
#5600
1%
0G
1P
1Q
0&
0H
0J
1=
19
0<
0@
0>
0?
0(
0;
b111001 1
1,
0+
0*
0)
#5700
1'
1(
1;
b111010 1
1)
#5800
1&
1M
1>
1?
0(
0;
b111011 1
1*
0)
#5900
1#
0$
1F
1B
0%
1I
0&
0'
1J
1(
1;
b111100 1
1)
#6000
0B
0$
0F
1K
0A
0%
0Q
1C
0I
0P
1&
0L
1D
0J
1<
1@
0>
0?
0(
0;
b111101 1
1+
0*
0)
#6100
1'
1(
1;
b111110 1
1)
#6200
1%
0&
1Q
0M
1H
1>
1?
0(
0;
b111111 1
1*
0)
#6300
1&
0'
1J
1(
1;
b1000000 1
1)
#6400
0#
0%
0K
0C
0Q
0&
0D
0H
0J
0=
09
0<
0@
0>
0?
0(
0;
b1000001 1
1/
0.
0-
0,
0+
0*
0)
#6500
1&
12
b1000010 1
1)
#6600
1%
1Q
0&
13
02
b1000011 1
1*
0)
#6700
1&
12
b1000100 1
1)
#6800
1$
1A
0%
1P
0Q
0&
14
03
02
b1000101 1
1+
0*
0)
#6900
1&
12
b1000110 1
1)
#7000
1%
1Q
0&
13
02
b1000111 1
1*
0)
#7100
1&
12
b1001000 1
1)
#7200
0$
1#
0A
0%
1K
0P
0Q
0&
1:
04
03
02
b1001001 1
1,
0+
0*
0)
#7300
1&
12
b1001010 1
1)
#7400
1%
1Q
0&
13
02
b1001011 1
1*
0)
#7500
1&
12
b1001100 1
1)
#7600
1$
1A
0%
1P
0Q
0&
14
03
02
b1001101 1
1+
0*
0)
#7700
1&
12
b1001110 1
1)
#7800
1%
1Q
0&
13
02
b1001111 1
1*
0)
#7900
1&
12
b1010000 1
1)
#8000
0$
0#
0A
0%
0K
0P
0Q
0&
0:
04
03
02
b1010001 1
1-
0,
0+
0*
0)
#8100
1&
1(
12
b1010010 1
1)
#8200
1%
1Q
0&
1'
1>
13
0(
02
b1010011 1
1*
0)
#8300
1&
1(
12
b1010100 1
1)
#8400
1$
1A
0%
1P
0Q
1&
1M
0'
1<
14
0>
03
0(
02
b1010101 1
1+
0*
0)
#8500
1%
1I
0&
1(
12
b1010110 1
1)
#8600
0I
1Q
1&
1'
1>
13
0(
02
b1010111 1
1*
0)
#8700
1#
0$
1F
1B
0%
1I
0&
1(
12
b1011000 1
1)
#8800
1%
0"
0F
0B
0E
1#
0A
0I
1K
0P
1Q
0&
1L
0M
0'
1=
1:
0<
04
0>
03
0(
02
b1011001 1
1,
0+
0*
0)
#8900
1&
1(
12
b1011010 1
1)
#9000
1$
0%
1A
1G
0Q
0&
1'
1>
13
0(
02
b1011011 1
1*
0)
#9100
1&
1(
12
b1011100 1
1)
#9200
1%
0G
1P
1Q
1&
1M
0'
1<
14
0>
03
0(
02
b1011101 1
1+
0*
0)
#9300
1"
1E
0#
0$
1F
1B
0%
1I
0&
1(
12
b1011110 1
1)
#9400
1"
1E
0#
1O
0B
0$
0F
0A
1G
0I
0Q
1&
1'
1>
13
0(
02
b1011111 1
1*
0)
#9500
1%
1I
0&
1(
12
b1100000 1
1)
#9600
0"
0%
0E
0O
0#
0G
0I
0K
0P
0Q
0&
0L
0M
0'
0=
0:
0<
04
0>
03
0(
02
b1100001 1
1.
0-
0,
0+
0*
0)
#9700
1&
1'
1;
12
b1100010 1
1)
#9800
1%
1Q
1&
1M
0'
1?
13
0;
02
b1100011 1
1*
0)
#9900
1$
1B
0%
1I
0&
1'
1;
12
b1100100 1
1)
#10000
1%
0B
1A
0I
1P
1Q
0&
1L
0M
0'
1@
14
0?
03
0;
02
b1100101 1
1+
0*
0)
#10100
1&
1'
1;
12
b1100110 1
1)
#10200
1#
1O
0$
0%
0A
1G
0Q
1&
1M
0'
1?
13
0;
02
b1100111 1
1*
0)
#10300
1%
1I
0&
1'
1;
12
b1101000 1
1)
#10400
0"
0O
0E
0%
1$
1#
1A
0G
0I
1K
0Q
0&
0L
0M
0'
19
1:
0@
04
0?
03
0;
02
b1101001 1
1,
0+
0*
0)
#10500
1&
1'
1;
12
b1101010 1
1)
#10600
1%
1Q
1&
1M
0'
1?
13
0;
02
b1101011 1
1*
0)
#10700
1"
1E
0#
0$
1F
1B
0%
1I
0&
1'
1;
12
b1101100 1
1)
#10800
0!
0E
1%
0F
1N
0B
0A
0K
1C
0I
0P
1Q
0&
1L
0M
0'
1@
14
0?
03
0;
02
b1101101 1
1+
0*
0)
#10900
1&
1'
1;
12
b1101110 1
1)
#11000
1$
0%
1A
1G
0Q
1&
1M
0'
1?
13
0;
02
b1101111 1
1*
0)
#11100
1%
1I
0&
1'
1;
12
b1110000 1
1)
#11200
0%
0$
0#
0"
0A
0C
0G
0I
0K
0N
0Q
0&
0L
0M
0'
09
0:
0@
04
0?
03
0;
02
b1110001 1
1-
0,
0+
0*
0)
#11300
1&
1'
1(
1;
12
b1110010 1
1)
#11400
1%
1Q
1&
1M
1>
1?
13
0(
0;
02
b1110011 1
1*
0)
#11500
1$
1B
0%
1I
0'
1J
1(
1;
12
b1110100 1
1)
#11600
1%
0B
1A
0I
1P
1Q
1L
0J
1<
1@
14
0>
0?
03
0(
0;
02
b1110101 1
1+
0*
0)
#11700
1#
0$
1F
1B
0%
1I
0&
1'
1(
1;
12
b1110110 1
1)
#11800
1#
1O
0B
0$
0F
0A
1%
1G
0I
0&
0M
1H
1>
1?
13
0(
0;
02
b1110111 1
1*
0)
#11900
1$
1B
0%
1I
0'
1J
1(
1;
12
b1111000 1
1)
#12000
0"
0O
0B
0E
1$
0F
1#
1A
1%
0G
0I
1K
0H
0J
1=
19
1:
0<
0@
04
0>
0?
03
0(
0;
02
b1111001 1
1,
0+
0*
0)
#12100
1&
1'
1(
1;
12
b1111010 1
1)
#12200
1"
1E
0#
1O
0$
0%
0A
1G
0Q
1&
1M
1>
1?
13
0(
0;
02
b1111011 1
1*
0)
#12300
1%
1I
0'
1J
1(
1;
12
b1111100 1
1)
#12400
0!
0E
1"
0#
0O
0%
1N
1$
0K
1A
1C
0G
0I
0Q
0L
1D
0J
1<
1@
14
0>
0?
03
0(
0;
02
b1111101 1
1+
0*
0)
#12500
1%
1I
0&
1'
1(
1;
12
b1111110 1
1)
#12600
1#
1O
0$
0A
1G
0%
0I
0&
0M
1H
1>
1?
13
0(
0;
02
b1111111 1
1*
0)
#12700
1%
1I
0'
1J
1(
1;
12
b10000000 1
1)
#12800
0E
0O
0#
0"
0%
0G
0I
0C
0K
0N
0P
0D
0H
0J
0=
09
0:
0<
0@
04
0>
0?
03
0(
0;
02
b10000001 1
10
0/
0.
0-
0,
0+
0*
0)
#12900
1%
16
b10000010 1
1)
#13000
1$
1A
0%
17
06
b10000011 1
1*
0)
#13100
1%
16
b10000100 1
1)
#13200
1#
0$
1K
0A
0%
15
07
06
b10000101 1
1+
0*
0)
#13300
1%
16
b10000110 1
1)
#13400
1$
1A
0%
17
06
b10000111 1
1*
0)
#13500
1%
16
b10001000 1
1)
#13600
0#
0$
1"
0K
0A
0%
18
05
07
06
b10001001 1
1,
0+
0*
0)
#13700
1%
16
b10001010 1
1)
#13800
1$
1A
0%
17
06
b10001011 1
1*
0)
#13900
1%
16
b10001100 1
1)
#14000
1#
0$
1K
0A
0%
15
07
06
b10001101 1
1+
0*
0)
#14100
1%
16
b10001110 1
1)
#14200
1$
1A
0%
17
06
b10001111 1
1*
0)
#14300
1%
16
b10010000 1
1)
#14400
0#
0$
0"
0K
0A
0%
08
05
07
06
b10010001 1
1-
0,
0+
0*
0)
#14500
1%
1(
16
b10010010 1
1)
#14600
1$
1A
0%
1'
1>
17
0(
06
b10010011 1
1*
0)
#14700
1%
1(
16
b10010100 1
1)
#14800
1#
1&
0$
1K
0A
0%
1M
0'
1<
15
0>
07
0(
06
b10010101 1
1+
0*
0)
#14900
1%
1(
16
b10010110 1
1)
#15000
1$
1A
0%
1'
1>
17
0(
06
b10010111 1
1*
0)
#15100
1%
1(
16
b10011000 1
1)
#15200
0#
1Q
0&
0$
1"
0K
0A
1%
1L
0M
0'
1=
18
0<
05
0>
07
0(
06
b10011001 1
1,
0+
0*
0)
#15300
1$
1B
0%
1(
16
b10011010 1
1)
#15400
0B
1A
1%
1'
1>
17
0(
06
b10011011 1
1*
0)
#15500
1#
0$
1F
1B
0%
1(
16
b10011100 1
1)
#15600
1&
0F
0B
1K
0A
1%
1M
0'
1<
15
0>
07
0(
06
b10011101 1
1+
0*
0)
#15700
1$
1B
0%
1(
16
b10011110 1
1)
#15800
0B
1A
1%
1'
1>
17
0(
06
b10011111 1
1*
0)
#15900
1!
0"
1E
0#
0$
1F
1B
0%
1(
16
b10100000 1
1)
#16000
0E
0Q
0&
0F
0B
0"
0!
0K
0A
0%
0L
0M
0'
0=
08
0<
05
0>
07
0(
06
b10100001 1
1.
0-
0,
0+
0*
0)
#16100
1%
1'
1;
16
b10100010 1
1)
#16200
1&
1$
1A
0%
1M
0'
1?
17
0;
06
b10100011 1
1*
0)
#16300
1%
1'
1;
16
b10100100 1
1)
#16400
1#
1Q
0&
0$
1K
0A
1%
1L
0M
0'
1@
15
0?
07
0;
06
b10100101 1
1+
0*
0)
#16500
1$
1B
0%
1'
1;
16
b10100110 1
1)
#16600
1&
0B
1A
1%
1M
0'
1?
17
0;
06
b10100111 1
1*
0)
#16700
1"
1E
0#
0$
1F
1B
0%
1'
1;
16
b10101000 1
1)
#16800
1$
0E
0Q
0&
0F
0B
1P
1"
0!
0K
1A
0%
0L
0M
0'
19
18
0@
05
0?
07
0;
06
b10101001 1
1,
0+
0*
0)
#16900
1%
1'
1;
16
b10101010 1
1)
#17000
1#
1&
0$
1O
0A
0%
1M
0'
1?
17
0;
06
b10101011 1
1*
0)
#17100
1%
1'
1;
16
b10101100 1
1)
#17200
1Q
0&
1$
0O
1K
1A
1%
1L
0M
0'
1@
15
0?
07
0;
06
b10101101 1
1+
0*
0)
#17300
1!
0"
1E
0#
0$
1F
1B
0%
1'
1;
16
b10101110 1
1)
#17400
1&
0F
1O
0B
0A
1%
1M
0'
1?
17
0;
06
b10101111 1
1*
0)
#17500
1$
1B
0%
1'
1;
16
b10110000 1
1)
#17600
0$
0E
0Q
0&
0O
0B
0P
0"
0!
0K
0A
0%
0L
0M
0'
09
08
0@
05
0?
07
0;
06
b10110001 1
1-
0,
0+
0*
0)
#17700
1%
1'
1(
1;
16
b10110010 1
1)
#17800
1&
1$
1A
0%
1M
1>
1?
17
0(
0;
06
b10110011 1
1*
0)
#17900
1#
0$
1F
1B
1I
0&
0%
0'
1J
1(
1;
16
b10110100 1
1)
#18000
1Q
0I
0F
1K
0A
1&
1%
0B
1L
0J
1<
1@
15
0>
0?
07
0(
0;
06
b10110101 1
1+
0*
0)
#18100
1$
1B
0%
1'
1(
1;
16
b10110110 1
1)
#18200
1"
1E
0#
0$
1O
0&
1G
0B
0Q
0A
0%
0M
1H
1>
1?
17
0(
0;
06
b10110111 1
1*
0)
#18300
1&
1%
0'
1J
1(
1;
16
b10111000 1
1)
#18400
0E
0G
1$
1P
1"
0!
0K
1Q
1A
0O
0&
1%
0H
0J
1=
19
18
0<
0@
05
0>
0?
07
0(
0;
06
b10111001 1
1,
0+
0*
0)
#18500
1#
0$
1F
1B
0%
1'
1(
1;
16
b10111010 1
1)
#18600
1&
0F
1O
0B
0A
1%
1M
1>
1?
17
0(
0;
06
b10111011 1
1*
0)
#18700
1$
1I
1B
0&
1%
0'
1J
1(
1;
16
b10111100 1
1)
#18800
1N
1!
0B
0"
0E
0#
0Q
1C
0$
0F
0O
0I
0P
0K
0A
1&
0%
0L
1D
0J
1<
1@
15
0>
0?
07
0(
0;
06
b10111101 1
1+
0*
0)
#18900
1%
1'
1(
1;
16
b10111110 1
1)
#19000
0&
1$
1Q
1A
1%
0M
1H
1>
1?
17
0(
0;
06
b10111111 1
1*
0)
#19100
1#
0$
1F
1B
1&
0%
0'
1J
1(
1;
16
b11000000 1
1)
#19200
0#
0!
0N
0F
0B
0C
0"
0K
0Q
0A
0&
0%
0D
0H
0J
0=
09
08
0<
0@
05
0>
0?
07
0(
0;
06
b11000001 1
1/
0.
0-
0,
0+
0*
0)
#19300
1&
1%
12
16
b11000010 1
1)
#19400
1$
1Q
1A
0&
1%
13
17
02
06
b11000011 1
1*
0)
#19500
1#
0$
1F
1B
1&
0%
12
16
b11000100 1
1)
#19600
1$
0F
0B
1P
1K
0Q
1A
0&
0%
14
15
03
07
02
06
b11000101 1
1+
0*
0)
#19700
1&
1%
12
16
b11000110 1
1)
#19800
1"
1E
0#
0$
1O
1Q
0A
0&
1%
13
17
02
06
b11000111 1
1*
0)
#19900
1$
1B
1&
0%
12
16
b11001000 1
1)
#20000
0E
0$
1#
0O
0B
1"
0!
0P
0Q
0A
0&
0%
1:
18
04
05
03
07
02
06
b11001001 1
1,
0+
0*
0)
#20100
1&
1%
12
16
b11001010 1
1)
#20200
1$
1Q
1A
0&
1%
13
17
02
06
b11001011 1
1*
0)
#20300
1!
0"
1E
0#
0$
1F
1B
1&
0%
12
16
b11001100 1
1)
#20400
1$
0E
1N
0F
0B
1P
0K
0Q
1A
0&
0%
14
15
03
07
02
06
b11001101 1
1+
0*
0)
#20500
1&
1%
12
16
b11001110 1
1)
#20600
1#
0$
1O
1Q
0A
0&
1%
13
17
02
06
b11001111 1
1*
0)
#20700
1$
1B
1&
0%
12
16
b11010000 1
1)
#20800
0$
0#
0!
0N
0O
0B
0"
0P
0Q
0A
0&
0%
0:
08
04
05
03
07
02
06
b11010001 1
1-
0,
0+
0*
0)
#20900
1&
1%
1(
12
16
b11010010 1
1)
#21000
1$
1Q
1A
0&
1%
1'
1>
13
17
0(
02
06
b11010011 1
1*
0)
#21100
1#
0$
1F
1B
1&
0%
1(
12
16
b11010100 1
1)
#21200
1$
0F
0B
1P
1K
0Q
1A
1&
0%
1M
0'
1<
14
15
0>
03
07
0(
02
06
b11010101 1
1+
0*
0)
#21300
1"
1E
0#
0$
1F
1B
1I
0&
0%
1(
12
16
b11010110 1
1)
#21400
1"
1E
0#
1O
0I
0F
1Q
0A
1&
1%
0B
1'
1>
13
17
0(
02
06
b11010111 1
1*
0)
#21500
1$
1I
1B
0&
1%
1(
12
16
b11011000 1
1)
#21600
0E
1#
0B
0$
0F
0O
0I
1"
0!
0P
1Q
0A
0&
1%
1L
0M
0'
1=
1:
18
0<
04
05
0>
03
07
0(
02
06
b11011001 1
1,
0+
0*
0)
#21700
1$
1B
1&
0%
1(
12
16
b11011010 1
1)
#21800
1!
0"
1E
0#
0$
1O
1G
0B
0Q
0A
0&
0%
1'
1>
13
17
0(
02
06
b11011011 1
1*
0)
#21900
1&
1%
1(
12
16
b11011100 1
1)
#22000
0E
1N
0G
1$
1P
0K
1Q
1A
0O
1&
1%
1M
0'
1<
14
15
0>
03
07
0(
02
06
b11011101 1
1+
0*
0)
#22100
1#
0$
1F
1I
1B
0&
1%
1(
12
16
b11011110 1
1)
#22200
0"
0E
1#
0B
1G
1$
0F
1O
0I
0Q
1A
1&
0%
1'
1>
13
17
0(
02
06
b11011111 1
1*
0)
#22300
1"
1E
0#
0$
1F
1B
1I
0&
0%
1(
12
16
b11100000 1
1)
#22400
0!
0E
0O
0#
0N
0G
0I
0F
0"
0P
0Q
0A
0&
0%
0B
0L
0M
0'
0=
0:
08
0<
04
05
0>
03
07
0(
02
06
b11100001 1
1.
0-
0,
0+
0*
0)
#22500
1&
1%
1'
1;
12
16
b11100010 1
1)
#22600
1$
1Q
1A
1&
1%
1M
0'
1?
13
17
0;
02
06
b11100011 1
1*
0)
#22700
1#
0$
1F
1I
1B
0&
1%
1'
1;
12
16
b11100100 1
1)
#22800
0B
1$
0F
0I
1P
1K
1Q
1A
0&
1%
1L
0M
0'
1@
14
15
0?
03
07
0;
02
06
b11100101 1
1+
0*
0)
#22900
1"
1E
0#
0$
1F
1B
1&
0%
1'
1;
12
16
b11100110 1
1)
#23000
1$
1G
0F
1O
0B
0Q
1A
1&
0%
1M
0'
1?
13
17
0;
02
06
b11100111 1
1*
0)
#23100
1#
0$
1F
1B
1I
0&
0%
1'
1;
12
16
b11101000 1
1)
#23200
0E
0O
1$
1#
0G
0I
0F
1"
0!
0Q
1A
0&
0%
0B
0L
0M
0'
19
1:
18
0@
04
05
0?
03
07
0;
02
06
b11101001 1
1,
0+
0*
0)
#23300
1&
1%
1'
1;
12
16
b11101010 1
1)
#23400
1!
0"
1E
0#
0$
1O
1Q
0A
1&
1%
1M
0'
1?
13
17
0;
02
06
b11101011 1
1*
0)
#23500
1$
1I
1B
0&
1%
1'
1;
12
16
b11101100 1
1)
#23600
0E
0"
0B
1#
1C
1N
0$
0F
0O
0I
0P
1K
1Q
0A
0&
1%
1L
0M
0'
1@
14
15
0?
03
07
0;
02
06
b11101101 1
1+
0*
0)
#23700
1$
1B
1&
0%
1'
1;
12
16
b11101110 1
1)
#23800
1"
1E
0#
0$
1O
1G
0B
0Q
0A
1&
0%
1M
0'
1?
13
17
0;
02
06
b11101111 1
1*
0)
#23900
1$
1B
1I
0&
0%
1'
1;
12
16
b11110000 1
1)
#24000
0!
0$
0E
0K
0#
0C
0G
0I
0N
0"
0Q
0A
0O
0&
0%
0B
0L
0M
0'
09
0:
08
0@
04
05
0?
03
07
0;
02
06
b11110001 1
1-
0,
0+
0*
0)
#24100
1&
1%
1'
1(
1;
12
16
b11110010 1
1)
#24200
1$
1Q
1A
1&
1%
1M
1>
1?
13
17
0(
0;
02
06
b11110011 1
1*
0)
#24300
1#
0$
1F
1I
1B
1%
0'
1J
1(
1;
12
16
b11110100 1
1)
#24400
0B
1$
0F
0I
1P
1K
1Q
1A
1%
1L
0J
1<
1@
14
15
0>
0?
03
07
0(
0;
02
06
b11110101 1
1+
0*
0)
#24500
1"
1E
0#
0$
1F
1I
1B
0&
1%
1'
1(
1;
12
16
b11110110 1
1)
#24600
0#
0B
1G
1$
0F
1O
0I
1A
0&
1%
0M
1H
1>
1?
13
17
0(
0;
02
06
b11110111 1
1*
0)
#24700
1#
1I
0$
1F
1B
1%
0'
1J
1(
1;
12
16
b11111000 1
1)
#24800
0E
0O
0B
1#
0G
1$
0F
0I
1"
0!
1A
1%
0H
0J
1=
19
1:
18
0<
0@
04
05
0>
0?
03
07
0(
0;
02
06
b11111001 1
1,
0+
0*
0)
#24900
1!
0"
1E
0#
0$
1F
1B
1&
0%
1'
1(
1;
12
16
b11111010 1
1)
#25000
1$
1G
0F
1O
0B
0Q
1A
1&
0%
1M
1>
1?
13
17
0(
0;
02
06
b11111011 1
1*
0)
